{
  "appInfo" : {
    "build" : "233.11799.259",
    "buildDate" : "2023-12-03T20:43:00Z[UTC]",
    "productCode" : "PC",
    "generated" : "2023-12-11T06:03:16.192610574Z",
    "os" : "Linux 6.2.0-37-generic",
    "runtime" : "JetBrains s.r.o. 17.0.9 17.0.9+7-b1087.7"
  },
  "runtimeInfo" : {
    "maxMemory" : 1572864000,
    "numberOfProcessors" : 8,
    "maxNumberOfIndexingThreads" : 7,
    "maxSizeOfFileForIntelliSense" : 2560000,
    "maxSizeOfFileForContentLoading" : 20971520
  },
  "type" : "DumbIndexing",
  "projectIndexingActivityHistory" : {
    "projectName" : "PyCharmLearningProject",
    "times" : {
      "scanningIds" : [ 0, 1 ],
      "contentLoadingVisibleTime" : 1483271301,
      "retrievingChangedDuringIndexingFilesTime" : 332105,
      "separateApplyingIndexesVisibleTime" : 1812819139,
      "updatingStart" : "2023-12-11T06:03:07.326750432Z",
      "updatingEnd" : "2023-12-11T06:03:16.191715325Z",
      "totalWallTimeWithPauses" : 8864970860,
      "wallTimeOnPause" : 0,
      "wasInterrupted" : false,
      "dumbModeStart" : "2023-12-11T06:03:07.326750432Z",
      "dumbWallTimeWithPauses" : 8864970860,
      "dumbWallTimeWithoutPauses" : 8864970860,
      "totalWallTimeWithoutPauses" : 8864970860
    },
    "fileCount" : {
      "numberOfChangedDuringIndexingFiles" : 60,
      "numberOfFilesIndexedByInfrastructureExtensionsDuringIndexingStage" : 4617,
      "numberOfFilesIndexedWithLoadingContent" : 6341,
      "numberOfNothingToWriteFiles" : 1368
    },
    "totalStatsPerFileType" : [ {
      "fileType" : "PythonStub",
      "partOfTotalProcessingTime" : {
        "part" : 18286502132,
        "total" : 30428748755
      },
      "partOfTotalContentLoadingTime" : {
        "part" : 4425424263,
        "total" : 5142454331
      },
      "totalNumberOfFiles" : 4305,
      "totalFilesSize" : 10042820,
      "totalProcessingSpeed" : {
        "totalBytes" : 10042820,
        "totalCpuTime" : 18286502132
      },
      "biggestContributors" : [ {
        "providerName" : "Python SDK Python 3.10 (PyCharmLearningProject) /home/olenepal/.cache/JetBrains/PyCharmCE2023.3/demo/PyCharmLearningProject/venv/bin/python",
        "numberOfFiles" : 4305,
        "totalFilesSize" : 10042820,
        "partOfTotalProcessingTimeOfThisFileType" : {
          "part" : 18286502132,
          "total" : 18286502132
        }
      } ]
    }, {
      "fileType" : "Python",
      "partOfTotalProcessingTime" : {
        "part" : 6863124368,
        "total" : 30428748755
      },
      "partOfTotalContentLoadingTime" : {
        "part" : 296245558,
        "total" : 5142454331
      },
      "totalNumberOfFiles" : 1491,
      "totalFilesSize" : 20407576,
      "totalProcessingSpeed" : {
        "totalBytes" : 20407576,
        "totalCpuTime" : 6863124368
      },
      "biggestContributors" : [ {
        "providerName" : "Python SDK Python 3.10 (PyCharmLearningProject) /home/olenepal/.cache/JetBrains/PyCharmCE2023.3/demo/PyCharmLearningProject/venv/bin/python",
        "numberOfFiles" : 50,
        "totalFilesSize" : 857708,
        "partOfTotalProcessingTimeOfThisFileType" : {
          "part" : 3007896543,
          "total" : 6863124368
        }
      }, {
        "providerName" : "Python SDK Python 3.10 (PyCharmLearningProject) /home/olenepal/.cache/JetBrains/PyCharmCE2023.3/demo/PyCharmLearningProject/venv/bin/python",
        "numberOfFiles" : 1373,
        "totalFilesSize" : 18894958,
        "partOfTotalProcessingTimeOfThisFileType" : {
          "part" : 1968883555,
          "total" : 6863124368
        }
      }, {
        "providerName" : "Refreshed files",
        "numberOfFiles" : 59,
        "totalFilesSize" : 643579,
        "partOfTotalProcessingTimeOfThisFileType" : {
          "part" : 1879779653,
          "total" : 6863124368
        }
      }, {
        "providerName" : "Module 'PyCharmLearningProject' (all roots)",
        "numberOfFiles" : 9,
        "totalFilesSize" : 11331,
        "partOfTotalProcessingTimeOfThisFileType" : {
          "part" : 6564617,
          "total" : 6863124368
        }
      } ]
    }, {
      "fileType" : "PLAIN_TEXT",
      "partOfTotalProcessingTime" : {
        "part" : 1823829732,
        "total" : 30428748755
      },
      "partOfTotalContentLoadingTime" : {
        "part" : 177939198,
        "total" : 5142454331
      },
      "totalNumberOfFiles" : 171,
      "totalFilesSize" : 549703,
      "totalProcessingSpeed" : {
        "totalBytes" : 549703,
        "totalCpuTime" : 1823829732
      },
      "biggestContributors" : [ {
        "providerName" : "Python SDK Python 3.10 (PyCharmLearningProject) /home/olenepal/.cache/JetBrains/PyCharmCE2023.3/demo/PyCharmLearningProject/venv/bin/python",
        "numberOfFiles" : 169,
        "totalFilesSize" : 548393,
        "partOfTotalProcessingTimeOfThisFileType" : {
          "part" : 1819875997,
          "total" : 1823829732
        }
      }, {
        "providerName" : "Indexable set contributor 'com.intellij.javaee.ExternalResourcesRootsProvider@4c506270' (non-project)",
        "numberOfFiles" : 1,
        "totalFilesSize" : 1296,
        "partOfTotalProcessingTimeOfThisFileType" : {
          "part" : 2085135,
          "total" : 1823829732
        }
      }, {
        "providerName" : "Module 'PyCharmLearningProject' (all roots)",
        "numberOfFiles" : 1,
        "totalFilesSize" : 14,
        "partOfTotalProcessingTimeOfThisFileType" : {
          "part" : 1868600,
          "total" : 1823829732
        }
      } ]
    }, {
      "fileType" : "XML",
      "partOfTotalProcessingTime" : {
        "part" : 1406171615,
        "total" : 30428748755
      },
      "partOfTotalContentLoadingTime" : {
        "part" : 17383676,
        "total" : 5142454331
      },
      "totalNumberOfFiles" : 16,
      "totalFilesSize" : 706614,
      "totalProcessingSpeed" : {
        "totalBytes" : 706614,
        "totalCpuTime" : 1406171615
      },
      "biggestContributors" : [ {
        "providerName" : "Indexable set contributor 'com.intellij.javaee.ExternalResourcesRootsProvider@4c506270' (non-project)",
        "numberOfFiles" : 15,
        "totalFilesSize" : 705986,
        "partOfTotalProcessingTimeOfThisFileType" : {
          "part" : 1284799378,
          "total" : 1406171615
        }
      }, {
        "providerName" : "Python SDK Python 3.10 (PyCharmLearningProject) /home/olenepal/.cache/JetBrains/PyCharmCE2023.3/demo/PyCharmLearningProject/venv/bin/python",
        "numberOfFiles" : 1,
        "totalFilesSize" : 628,
        "partOfTotalProcessingTimeOfThisFileType" : {
          "part" : 121372237,
          "total" : 1406171615
        }
      } ]
    }, {
      "fileType" : "DTD",
      "partOfTotalProcessingTime" : {
        "part" : 667788630,
        "total" : 30428748755
      },
      "partOfTotalContentLoadingTime" : {
        "part" : 34512788,
        "total" : 5142454331
      },
      "totalNumberOfFiles" : 61,
      "totalFilesSize" : 593925,
      "totalProcessingSpeed" : {
        "totalBytes" : 593925,
        "totalCpuTime" : 667788630
      },
      "biggestContributors" : [ {
        "providerName" : "Indexable set contributor 'com.intellij.javaee.ExternalResourcesRootsProvider@4c506270' (non-project)",
        "numberOfFiles" : 61,
        "totalFilesSize" : 593925,
        "partOfTotalProcessingTimeOfThisFileType" : {
          "part" : 667788630,
          "total" : 667788630
        }
      } ]
    }, {
      "fileType" : "TOML",
      "partOfTotalProcessingTime" : {
        "part" : 441360641,
        "total" : 30428748755
      },
      "partOfTotalContentLoadingTime" : {
        "part" : 124623035,
        "total" : 5142454331
      },
      "totalNumberOfFiles" : 148,
      "totalFilesSize" : 22645,
      "totalProcessingSpeed" : {
        "totalBytes" : 22645,
        "totalCpuTime" : 441360641
      },
      "biggestContributors" : [ {
        "providerName" : "Python SDK Python 3.10 (PyCharmLearningProject) /home/olenepal/.cache/JetBrains/PyCharmCE2023.3/demo/PyCharmLearningProject/venv/bin/python",
        "numberOfFiles" : 148,
        "totalFilesSize" : 22645,
        "partOfTotalProcessingTimeOfThisFileType" : {
          "part" : 441360641,
          "total" : 441360641
        }
      } ]
    }, {
      "fileType" : "RNG Compact",
      "partOfTotalProcessingTime" : {
        "part" : 400150771,
        "total" : 30428748755
      },
      "partOfTotalContentLoadingTime" : {
        "part" : 42498290,
        "total" : 5142454331
      },
      "totalNumberOfFiles" : 124,
      "totalFilesSize" : 476287,
      "totalProcessingSpeed" : {
        "totalBytes" : 476287,
        "totalCpuTime" : 400150771
      },
      "biggestContributors" : [ {
        "providerName" : "Indexable set contributor 'com.intellij.javaee.ExternalResourcesRootsProvider@4c506270' (non-project)",
        "numberOfFiles" : 124,
        "totalFilesSize" : 476287,
        "partOfTotalProcessingTimeOfThisFileType" : {
          "part" : 400150771,
          "total" : 400150771
        }
      } ]
    }, {
      "fileType" : "Markdown",
      "partOfTotalProcessingTime" : {
        "part" : 286301195,
        "total" : 30428748755
      },
      "partOfTotalContentLoadingTime" : {
        "part" : 1960705,
        "total" : 5142454331
      },
      "totalNumberOfFiles" : 3,
      "totalFilesSize" : 12456,
      "totalProcessingSpeed" : {
        "totalBytes" : 12456,
        "totalCpuTime" : 286301195
      },
      "biggestContributors" : [ {
        "providerName" : "Module 'PyCharmLearningProject' (all roots)",
        "numberOfFiles" : 1,
        "totalFilesSize" : 2281,
        "partOfTotalProcessingTimeOfThisFileType" : {
          "part" : 260718857,
          "total" : 286301195
        }
      }, {
        "providerName" : "Python SDK Python 3.10 (PyCharmLearningProject) /home/olenepal/.cache/JetBrains/PyCharmCE2023.3/demo/PyCharmLearningProject/venv/bin/python",
        "numberOfFiles" : 2,
        "totalFilesSize" : 10175,
        "partOfTotalProcessingTimeOfThisFileType" : {
          "part" : 25582338,
          "total" : 286301195
        }
      } ]
    }, {
      "fileType" : "textmate",
      "partOfTotalProcessingTime" : {
        "part" : 81243787,
        "total" : 30428748755
      },
      "partOfTotalContentLoadingTime" : {
        "part" : 6811538,
        "total" : 5142454331
      },
      "totalNumberOfFiles" : 5,
      "totalFilesSize" : 106492,
      "totalProcessingSpeed" : {
        "totalBytes" : 106492,
        "totalCpuTime" : 81243787
      },
      "biggestContributors" : [ {
        "providerName" : "Python SDK Python 3.10 (PyCharmLearningProject) /home/olenepal/.cache/JetBrains/PyCharmCE2023.3/demo/PyCharmLearningProject/venv/bin/python",
        "numberOfFiles" : 5,
        "totalFilesSize" : 106492,
        "partOfTotalProcessingTimeOfThisFileType" : {
          "part" : 81243787,
          "total" : 81243787
        }
      } ]
    }, {
      "fileType" : "Shell Script",
      "partOfTotalProcessingTime" : {
        "part" : 72223367,
        "total" : 30428748755
      },
      "partOfTotalContentLoadingTime" : {
        "part" : 661616,
        "total" : 5142454331
      },
      "totalNumberOfFiles" : 2,
      "totalFilesSize" : 23223,
      "totalProcessingSpeed" : {
        "totalBytes" : 23223,
        "totalCpuTime" : 72223367
      },
      "biggestContributors" : [ {
        "providerName" : "Python SDK Python 3.10 (PyCharmLearningProject) /home/olenepal/.cache/JetBrains/PyCharmCE2023.3/demo/PyCharmLearningProject/venv/bin/python",
        "numberOfFiles" : 2,
        "totalFilesSize" : 23223,
        "partOfTotalProcessingTimeOfThisFileType" : {
          "part" : 72223367,
          "total" : 72223367
        }
      } ]
    }, {
      "fileType" : "ReST",
      "partOfTotalProcessingTime" : {
        "part" : 34311998,
        "total" : 30428748755
      },
      "partOfTotalContentLoadingTime" : {
        "part" : 889647,
        "total" : 5142454331
      },
      "totalNumberOfFiles" : 1,
      "totalFilesSize" : 9561,
      "totalProcessingSpeed" : {
        "totalBytes" : 9561,
        "totalCpuTime" : 34311998
      },
      "biggestContributors" : [ {
        "providerName" : "Python SDK Python 3.10 (PyCharmLearningProject) /home/olenepal/.cache/JetBrains/PyCharmCE2023.3/demo/PyCharmLearningProject/venv/bin/python",
        "numberOfFiles" : 1,
        "totalFilesSize" : 9561,
        "partOfTotalProcessingTimeOfThisFileType" : {
          "part" : 34311998,
          "total" : 34311998
        }
      } ]
    }, {
      "fileType" : "C++",
      "partOfTotalProcessingTime" : {
        "part" : 26753700,
        "total" : 30428748755
      },
      "partOfTotalContentLoadingTime" : {
        "part" : 751104,
        "total" : 5142454331
      },
      "totalNumberOfFiles" : 1,
      "totalFilesSize" : 5357,
      "totalProcessingSpeed" : {
        "totalBytes" : 5357,
        "totalCpuTime" : 26753700
      },
      "biggestContributors" : [ {
        "providerName" : "Python SDK Python 3.10 (PyCharmLearningProject) /home/olenepal/.cache/JetBrains/PyCharmCE2023.3/demo/PyCharmLearningProject/venv/bin/python",
        "numberOfFiles" : 1,
        "totalFilesSize" : 5357,
        "partOfTotalProcessingTimeOfThisFileType" : {
          "part" : 26753700,
          "total" : 26753700
        }
      } ]
    }, {
      "fileType" : "PATCH",
      "partOfTotalProcessingTime" : {
        "part" : 12470422,
        "total" : 30428748755
      },
      "partOfTotalContentLoadingTime" : {
        "part" : 1762998,
        "total" : 5142454331
      },
      "totalNumberOfFiles" : 8,
      "totalFilesSize" : 4449,
      "totalProcessingSpeed" : {
        "totalBytes" : 4449,
        "totalCpuTime" : 12470422
      },
      "biggestContributors" : [ {
        "providerName" : "Indexable set contributor 'com.intellij.javaee.ExternalResourcesRootsProvider@4c506270' (non-project)",
        "numberOfFiles" : 8,
        "totalFilesSize" : 4449,
        "partOfTotalProcessingTimeOfThisFileType" : {
          "part" : 12470422,
          "total" : 12470422
        }
      } ]
    }, {
      "fileType" : "GitIgnore file",
      "partOfTotalProcessingTime" : {
        "part" : 10722351,
        "total" : 30428748755
      },
      "partOfTotalContentLoadingTime" : {
        "part" : 10300821,
        "total" : 5142454331
      },
      "totalNumberOfFiles" : 1,
      "totalFilesSize" : 47,
      "totalProcessingSpeed" : {
        "totalBytes" : 47,
        "totalCpuTime" : 10722351
      },
      "biggestContributors" : [ {
        "providerName" : "Refreshed files",
        "numberOfFiles" : 1,
        "totalFilesSize" : 47,
        "partOfTotalProcessingTimeOfThisFileType" : {
          "part" : 10722351,
          "total" : 10722351
        }
      } ]
    }, {
      "fileType" : "CSS",
      "partOfTotalProcessingTime" : {
        "part" : 9533135,
        "total" : 30428748755
      },
      "partOfTotalContentLoadingTime" : {
        "part" : 596773,
        "total" : 5142454331
      },
      "totalNumberOfFiles" : 1,
      "totalFilesSize" : 96,
      "totalProcessingSpeed" : {
        "totalBytes" : 96,
        "totalCpuTime" : 9533135
      },
      "biggestContributors" : [ {
        "providerName" : "Python SDK Python 3.10 (PyCharmLearningProject) /home/olenepal/.cache/JetBrains/PyCharmCE2023.3/demo/PyCharmLearningProject/venv/bin/python",
        "numberOfFiles" : 1,
        "totalFilesSize" : 96,
        "partOfTotalProcessingTimeOfThisFileType" : {
          "part" : 9533135,
          "total" : 9533135
        }
      } ]
    }, {
      "fileType" : "AUTO_DETECTED",
      "partOfTotalProcessingTime" : {
        "part" : 6260911,
        "total" : 30428748755
      },
      "partOfTotalContentLoadingTime" : {
        "part" : 92321,
        "total" : 5142454331
      },
      "totalNumberOfFiles" : 3,
      "totalFilesSize" : 0,
      "totalProcessingSpeed" : {
        "totalBytes" : 0,
        "totalCpuTime" : 6260911
      },
      "biggestContributors" : [ {
        "providerName" : "Python SDK Python 3.10 (PyCharmLearningProject) /home/olenepal/.cache/JetBrains/PyCharmCE2023.3/demo/PyCharmLearningProject/venv/bin/python",
        "numberOfFiles" : 3,
        "totalFilesSize" : 0,
        "partOfTotalProcessingTimeOfThisFileType" : {
          "part" : 6260911,
          "total" : 6260911
        }
      } ]
    } ],
    "totalStatsPerBaseLanguage" : [ {
      "language" : "Python",
      "partOfTotalProcessingTime" : {
        "part" : 25149626500,
        "total" : 30428748755
      },
      "partOfTotalContentLoadingTime" : {
        "part" : 5438699889,
        "total" : 5142454331
      },
      "totalNumberOfFiles" : 5796,
      "totalFilesSize" : 30450396,
      "totalProcessingSpeed" : {
        "totalBytes" : 30450396,
        "totalCpuTime" : 25149626500
      }
    }, {
      "language" : "PythonStub",
      "partOfTotalProcessingTime" : {
        "part" : 18286502132,
        "total" : 30428748755
      },
      "partOfTotalContentLoadingTime" : {
        "part" : 9567878594,
        "total" : 5142454331
      },
      "totalNumberOfFiles" : 4305,
      "totalFilesSize" : 10042820,
      "totalProcessingSpeed" : {
        "totalBytes" : 10042820,
        "totalCpuTime" : 18286502132
      }
    }, {
      "language" : "XML",
      "partOfTotalProcessingTime" : {
        "part" : 2073960245,
        "total" : 30428748755
      },
      "partOfTotalContentLoadingTime" : {
        "part" : 5159838007,
        "total" : 5142454331
      },
      "totalNumberOfFiles" : 77,
      "totalFilesSize" : 1300539,
      "totalProcessingSpeed" : {
        "totalBytes" : 1300539,
        "totalCpuTime" : 2073960245
      }
    }, {
      "language" : "TEXT",
      "partOfTotalProcessingTime" : {
        "part" : 1823829732,
        "total" : 30428748755
      },
      "partOfTotalContentLoadingTime" : {
        "part" : 5320393529,
        "total" : 5142454331
      },
      "totalNumberOfFiles" : 171,
      "totalFilesSize" : 549703,
      "totalProcessingSpeed" : {
        "totalBytes" : 549703,
        "totalCpuTime" : 1823829732
      }
    }, {
      "language" : "DTD",
      "partOfTotalProcessingTime" : {
        "part" : 667788630,
        "total" : 30428748755
      },
      "partOfTotalContentLoadingTime" : {
        "part" : 5176967119,
        "total" : 5142454331
      },
      "totalNumberOfFiles" : 61,
      "totalFilesSize" : 593925,
      "totalProcessingSpeed" : {
        "totalBytes" : 593925,
        "totalCpuTime" : 667788630
      }
    }, {
      "language" : "TOML",
      "partOfTotalProcessingTime" : {
        "part" : 441360641,
        "total" : 30428748755
      },
      "partOfTotalContentLoadingTime" : {
        "part" : 5267077366,
        "total" : 5142454331
      },
      "totalNumberOfFiles" : 148,
      "totalFilesSize" : 22645,
      "totalProcessingSpeed" : {
        "totalBytes" : 22645,
        "totalCpuTime" : 441360641
      }
    }, {
      "language" : "RELAX-NG",
      "partOfTotalProcessingTime" : {
        "part" : 400150771,
        "total" : 30428748755
      },
      "partOfTotalContentLoadingTime" : {
        "part" : 5184952621,
        "total" : 5142454331
      },
      "totalNumberOfFiles" : 124,
      "totalFilesSize" : 476287,
      "totalProcessingSpeed" : {
        "totalBytes" : 476287,
        "totalCpuTime" : 400150771
      }
    }, {
      "language" : "Markdown",
      "partOfTotalProcessingTime" : {
        "part" : 286301195,
        "total" : 30428748755
      },
      "partOfTotalContentLoadingTime" : {
        "part" : 5144415036,
        "total" : 5142454331
      },
      "totalNumberOfFiles" : 3,
      "totalFilesSize" : 12456,
      "totalProcessingSpeed" : {
        "totalBytes" : 12456,
        "totalCpuTime" : 286301195
      }
    }, {
      "language" : "textmate",
      "partOfTotalProcessingTime" : {
        "part" : 81243787,
        "total" : 30428748755
      },
      "partOfTotalContentLoadingTime" : {
        "part" : 5149265869,
        "total" : 5142454331
      },
      "totalNumberOfFiles" : 5,
      "totalFilesSize" : 106492,
      "totalProcessingSpeed" : {
        "totalBytes" : 106492,
        "totalCpuTime" : 81243787
      }
    }, {
      "language" : "Shell Script",
      "partOfTotalProcessingTime" : {
        "part" : 72223367,
        "total" : 30428748755
      },
      "partOfTotalContentLoadingTime" : {
        "part" : 5143115947,
        "total" : 5142454331
      },
      "totalNumberOfFiles" : 2,
      "totalFilesSize" : 23223,
      "totalProcessingSpeed" : {
        "totalBytes" : 23223,
        "totalCpuTime" : 72223367
      }
    }, {
      "language" : "ReST",
      "partOfTotalProcessingTime" : {
        "part" : 34311998,
        "total" : 30428748755
      },
      "partOfTotalContentLoadingTime" : {
        "part" : 5143343978,
        "total" : 5142454331
      },
      "totalNumberOfFiles" : 1,
      "totalFilesSize" : 9561,
      "totalProcessingSpeed" : {
        "totalBytes" : 9561,
        "totalCpuTime" : 34311998
      }
    }, {
      "language" : "GitIgnore",
      "partOfTotalProcessingTime" : {
        "part" : 10722351,
        "total" : 30428748755
      },
      "partOfTotalContentLoadingTime" : {
        "part" : 5152755152,
        "total" : 5142454331
      },
      "totalNumberOfFiles" : 1,
      "totalFilesSize" : 47,
      "totalProcessingSpeed" : {
        "totalBytes" : 47,
        "totalCpuTime" : 10722351
      }
    }, {
      "language" : "IgnoreLang",
      "partOfTotalProcessingTime" : {
        "part" : 10722351,
        "total" : 30428748755
      },
      "partOfTotalContentLoadingTime" : {
        "part" : 5152755152,
        "total" : 5142454331
      },
      "totalNumberOfFiles" : 1,
      "totalFilesSize" : 47,
      "totalProcessingSpeed" : {
        "totalBytes" : 47,
        "totalCpuTime" : 10722351
      }
    } ],
    "totalStatsPerIndexer" : [ {
      "indexId" : "Stubs",
      "partOfTotalIndexingTime" : {
        "part" : 4335513528,
        "total" : 9131715807
      },
      "totalNumberOfFiles" : 4448,
      "totalNumberOfFilesIndexedByExtensions" : 4323,
      "totalFilesSize" : 12319125,
      "indexValueChangerEvaluationSpeed" : {
        "totalBytes" : 12319125,
        "totalCpuTime" : 4335513528
      }
    }, {
      "indexId" : "IdIndex",
      "partOfTotalIndexingTime" : {
        "part" : 3611842980,
        "total" : 9131715807
      },
      "totalNumberOfFiles" : 4962,
      "totalNumberOfFilesIndexedByExtensions" : 4617,
      "totalFilesSize" : 14106414,
      "indexValueChangerEvaluationSpeed" : {
        "totalBytes" : 14106414,
        "totalCpuTime" : 3611842980
      }
    }, {
      "indexId" : "Trigram.Index",
      "partOfTotalIndexingTime" : {
        "part" : 404909261,
        "total" : 9131715807
      },
      "totalNumberOfFiles" : 4973,
      "totalNumberOfFilesIndexedByExtensions" : 4617,
      "totalFilesSize" : 14110863,
      "indexValueChangerEvaluationSpeed" : {
        "totalBytes" : 14110863,
        "totalCpuTime" : 404909261
      }
    }, {
      "indexId" : "XmlNamespaces",
      "partOfTotalIndexingTime" : {
        "part" : 332255176,
        "total" : 9131715807
      },
      "totalNumberOfFiles" : 14,
      "totalNumberOfFilesIndexedByExtensions" : 0,
      "totalFilesSize" : 681985,
      "indexValueChangerEvaluationSpeed" : {
        "totalBytes" : 681985,
        "totalCpuTime" : 332255176
      }
    }, {
      "indexId" : "SchemaTypeInheritance",
      "partOfTotalIndexingTime" : {
        "part" : 194809658,
        "total" : 9131715807
      },
      "totalNumberOfFiles" : 11,
      "totalNumberOfFilesIndexedByExtensions" : 0,
      "totalFilesSize" : 415206,
      "indexValueChangerEvaluationSpeed" : {
        "totalBytes" : 415206,
        "totalCpuTime" : 194809658
      }
    }, {
      "indexId" : "XmlTagNames",
      "partOfTotalIndexingTime" : {
        "part" : 191489991,
        "total" : 9131715807
      },
      "totalNumberOfFiles" : 11,
      "totalNumberOfFilesIndexedByExtensions" : 0,
      "totalFilesSize" : 415206,
      "indexValueChangerEvaluationSpeed" : {
        "totalBytes" : 415206,
        "totalCpuTime" : 191489991
      }
    }, {
      "indexId" : "fileIncludes",
      "partOfTotalIndexingTime" : {
        "part" : 31410368,
        "total" : 9131715807
      },
      "totalNumberOfFiles" : 1,
      "totalNumberOfFilesIndexedByExtensions" : 1,
      "totalFilesSize" : 628,
      "indexValueChangerEvaluationSpeed" : {
        "totalBytes" : 628,
        "totalCpuTime" : 31410368
      }
    }, {
      "indexId" : "DomFileIndex",
      "partOfTotalIndexingTime" : {
        "part" : 29356663,
        "total" : 9131715807
      },
      "totalNumberOfFiles" : 16,
      "totalNumberOfFilesIndexedByExtensions" : 1,
      "totalFilesSize" : 706614,
      "indexValueChangerEvaluationSpeed" : {
        "totalBytes" : 706614,
        "totalCpuTime" : 29356663
      }
    }, {
      "indexId" : "RelaxSymbolIndex",
      "partOfTotalIndexingTime" : {
        "part" : 104644,
        "total" : 9131715807
      },
      "totalNumberOfFiles" : 1,
      "totalNumberOfFilesIndexedByExtensions" : 1,
      "totalFilesSize" : 628,
      "indexValueChangerEvaluationSpeed" : {
        "totalBytes" : 628,
        "totalCpuTime" : 104644
      }
    }, {
      "indexId" : "xmlProperties",
      "partOfTotalIndexingTime" : {
        "part" : 23538,
        "total" : 9131715807
      },
      "totalNumberOfFiles" : 1,
      "totalNumberOfFilesIndexedByExtensions" : 1,
      "totalFilesSize" : 628,
      "indexValueChangerEvaluationSpeed" : {
        "totalBytes" : 628,
        "totalCpuTime" : 23538
      }
    } ],
    "statisticsOfChangedDuringIndexingFiles" : {
      "numberOfFiles" : 60,
      "retrievingTime" : 332105
    },
    "fileProviderStatistics" : [ {
      "providerName" : "Python SDK Python 3.10 (PyCharmLearningProject) /home/olenepal/.cache/JetBrains/PyCharmCE2023.3/demo/PyCharmLearningProject/venv/bin/python",
      "totalNumberOfIndexedFiles" : 6011,
      "totalNumberOfFilesFullyIndexedByExtensions" : 4617,
      "totalNumberOfNothingToWriteFiles" : 1358,
      "totalIndexingVisibleTime" : 6599725475,
      "contentLoadingVisibleTime" : 1432698070,
      "numberOfTooLargeForIndexingFiles" : 0,
      "slowIndexedFiles" : [ {
        "fileName" : "cacert.pem",
        "processingTime" : 674962164,
        "evaluationOfIndexValueChangerTime" : 77734942,
        "contentLoadingTime" : 440623
      } ],
      "filesFullyIndexedByExtensions" : [ ],
      "separateApplyingIndexesVisibleTime" : 1428504039
    }, {
      "providerName" : "Python SDK Python 3.10 (PyCharmLearningProject) /home/olenepal/.cache/JetBrains/PyCharmCE2023.3/demo/PyCharmLearningProject/venv/bin/python",
      "totalNumberOfIndexedFiles" : 50,
      "totalNumberOfFilesFullyIndexedByExtensions" : 0,
      "totalNumberOfNothingToWriteFiles" : 0,
      "totalIndexingVisibleTime" : 867099452,
      "contentLoadingVisibleTime" : 11404566,
      "numberOfTooLargeForIndexingFiles" : 0,
      "slowIndexedFiles" : [ ],
      "filesFullyIndexedByExtensions" : [ ],
      "separateApplyingIndexesVisibleTime" : 122258462
    }, {
      "providerName" : "Indexable set contributor 'com.intellij.javaee.ExternalResourcesRootsProvider@4c506270' (non-project)",
      "totalNumberOfIndexedFiles" : 209,
      "totalNumberOfFilesFullyIndexedByExtensions" : 0,
      "totalNumberOfNothingToWriteFiles" : 0,
      "totalIndexingVisibleTime" : 682430260,
      "contentLoadingVisibleTime" : 27669554,
      "numberOfTooLargeForIndexingFiles" : 0,
      "slowIndexedFiles" : [ ],
      "filesFullyIndexedByExtensions" : [ ],
      "separateApplyingIndexesVisibleTime" : 163364126
    }, {
      "providerName" : "Refreshed files",
      "totalNumberOfIndexedFiles" : 60,
      "totalNumberOfFilesFullyIndexedByExtensions" : 0,
      "totalNumberOfNothingToWriteFiles" : 1,
      "totalIndexingVisibleTime" : 592561571,
      "contentLoadingVisibleTime" : 10381651,
      "numberOfTooLargeForIndexingFiles" : 0,
      "slowIndexedFiles" : [ ],
      "filesFullyIndexedByExtensions" : [ ],
      "separateApplyingIndexesVisibleTime" : 91978537
    }, {
      "providerName" : "Module 'PyCharmLearningProject' (all roots)",
      "totalNumberOfIndexedFiles" : 11,
      "totalNumberOfFilesFullyIndexedByExtensions" : 0,
      "totalNumberOfNothingToWriteFiles" : 9,
      "totalIndexingVisibleTime" : 77589641,
      "contentLoadingVisibleTime" : 1117460,
      "numberOfTooLargeForIndexingFiles" : 0,
      "slowIndexedFiles" : [ ],
      "filesFullyIndexedByExtensions" : [ ],
      "separateApplyingIndexesVisibleTime" : 6713975
    } ],
    "visibleTimeToAllThreadTimeRatio" : 0.31344138739140953
  }
}