{
  "appInfo" : {
    "build" : "233.11799.259",
    "buildDate" : "2023-12-03T20:43:00Z[UTC]",
    "productCode" : "PC",
    "generated" : "2023-12-12T09:34:14.425510879Z",
    "os" : "Linux 6.2.0-37-generic",
    "runtime" : "JetBrains s.r.o. 17.0.9 17.0.9+7-b1087.7"
  },
  "runtimeInfo" : {
    "maxMemory" : 2147483648,
    "numberOfProcessors" : 8,
    "maxNumberOfIndexingThreads" : 7,
    "maxSizeOfFileForIntelliSense" : 2560000,
    "maxSizeOfFileForContentLoading" : 20971520
  },
  "type" : "Scanning",
  "projectIndexingActivityHistory" : {
    "projectName" : "blogs",
    "times" : {
      "scanningReason" : "On project open",
      "scanningType" : "FULL_ON_PROJECT_OPEN",
      "scanningId" : 0,
      "creatingIteratorsTime" : 20543019,
      "concurrentHandlingWallTimeWithoutPauses" : 3622999335,
      "concurrentHandlingWallTimeWithPauses" : 3622999335,
      "concurrentHandlingSumOfThreadTimesWithPauses" : 6017830259,
      "concurrentIterationAndScannersApplicationSumOfThreadTimesWithPauses" : 1059133884,
      "concurrentFileCheckSumOfThreadTimesWithPauses" : 4943502433,
      "delayedPushPropertiesStageTime" : 752265,
      "indexExtensionsTime" : 0,
      "dumbWallTimeWithPauses" : 0,
      "dumbWallTimeWithoutPauses" : 0,
      "updatingStart" : "2023-12-12T09:34:10.564452272Z",
      "updatingEnd" : "2023-12-12T09:34:14.420491055Z",
      "totalWallTimeWithPauses" : 3856020120,
      "wallTimeOnPause" : 0,
      "wasInterrupted" : false,
      "totalWallTimeWithoutPauses" : 3856020120
    },
    "fileCount" : {
      "numberOfFileProviders" : 6,
      "numberOfScannedFiles" : 10468,
      "numberOfFilesIndexedByInfrastructureExtensionsDuringScan" : 0,
      "numberOfFilesScheduledForIndexingAfterScan" : 0
    },
    "scanningStatistics" : [ {
      "providerName" : "Python SDK Python 3.10 (blogs) /home/olenepal/blogs/.venv/bin/python",
      "numberOfScannedFiles" : 10231,
      "numberOfSkippedFiles" : 1,
      "numberOfFilesForIndexing" : 0,
      "numberOfFilesFullyIndexedByInfrastructureExtensions" : 0,
      "filesFullyIndexedByInfrastructureExtensions" : [ ],
      "statusTime" : 2024091873,
      "totalOneThreadTimeWithPauses" : 3579536338,
      "iterationAndScannersApplicationTime" : 1040851459,
      "filesCheckTime" : 2536084475,
      "timeProcessingUpToDateFiles" : 574060162,
      "timeUpdatingContentLessIndexes" : 4159055,
      "timeIndexingWithoutContentViaInfrastructureExtension" : 0,
      "roots" : [ ]
    }, {
      "providerName" : "Indexable set contributor 'com.intellij.javaee.ExternalResourcesRootsProvider@111f678f' (non-project)",
      "numberOfScannedFiles" : 209,
      "numberOfSkippedFiles" : 4,
      "numberOfFilesForIndexing" : 0,
      "numberOfFilesFullyIndexedByInfrastructureExtensions" : 0,
      "filesFullyIndexedByInfrastructureExtensions" : [ ],
      "statusTime" : 993831683,
      "totalOneThreadTimeWithPauses" : 1263953054,
      "iterationAndScannersApplicationTime" : 6567911,
      "filesCheckTime" : 1255696944,
      "timeProcessingUpToDateFiles" : 102923418,
      "timeUpdatingContentLessIndexes" : 0,
      "timeIndexingWithoutContentViaInfrastructureExtension" : 0,
      "roots" : [ ]
    }, {
      "providerName" : "Module 'blogs' (all roots)",
      "numberOfScannedFiles" : 28,
      "numberOfSkippedFiles" : 0,
      "numberOfFilesForIndexing" : 0,
      "numberOfFilesFullyIndexedByInfrastructureExtensions" : 0,
      "filesFullyIndexedByInfrastructureExtensions" : [ ],
      "statusTime" : 683737094,
      "totalOneThreadTimeWithPauses" : 1133025616,
      "iterationAndScannersApplicationTime" : 5871569,
      "filesCheckTime" : 1125273412,
      "timeProcessingUpToDateFiles" : 6808683,
      "timeUpdatingContentLessIndexes" : 140072,
      "timeIndexingWithoutContentViaInfrastructureExtension" : 0,
      "roots" : [ ]
    }, {
      "providerName" : "Indexable set contributor 'Scratches & Consoles' (non-project)",
      "numberOfScannedFiles" : 0,
      "numberOfSkippedFiles" : 0,
      "numberOfFilesForIndexing" : 0,
      "numberOfFilesFullyIndexedByInfrastructureExtensions" : 0,
      "filesFullyIndexedByInfrastructureExtensions" : [ ],
      "statusTime" : 0,
      "totalOneThreadTimeWithPauses" : 14721666,
      "iterationAndScannersApplicationTime" : 2773565,
      "filesCheckTime" : 9961051,
      "timeProcessingUpToDateFiles" : 0,
      "timeUpdatingContentLessIndexes" : 0,
      "timeIndexingWithoutContentViaInfrastructureExtension" : 0,
      "roots" : [ ]
    }, {
      "providerName" : "Indexable set contributor 'Scratches & Consoles' (project)",
      "numberOfScannedFiles" : 0,
      "numberOfSkippedFiles" : 0,
      "numberOfFilesForIndexing" : 0,
      "numberOfFilesFullyIndexedByInfrastructureExtensions" : 0,
      "filesFullyIndexedByInfrastructureExtensions" : [ ],
      "statusTime" : 0,
      "totalOneThreadTimeWithPauses" : 14248162,
      "iterationAndScannersApplicationTime" : 24594,
      "filesCheckTime" : 8910852,
      "timeProcessingUpToDateFiles" : 0,
      "timeUpdatingContentLessIndexes" : 0,
      "timeIndexingWithoutContentViaInfrastructureExtension" : 0,
      "roots" : [ ]
    }, {
      "providerName" : "Indexable set contributor 'com.intellij.javaee.ExternalResourcesRootsProvider@111f678f' (project)",
      "numberOfScannedFiles" : 0,
      "numberOfSkippedFiles" : 0,
      "numberOfFilesForIndexing" : 0,
      "numberOfFilesFullyIndexedByInfrastructureExtensions" : 0,
      "filesFullyIndexedByInfrastructureExtensions" : [ ],
      "statusTime" : 0,
      "totalOneThreadTimeWithPauses" : 12345423,
      "iterationAndScannersApplicationTime" : 3044786,
      "filesCheckTime" : 7575699,
      "timeProcessingUpToDateFiles" : 0,
      "timeUpdatingContentLessIndexes" : 0,
      "timeIndexingWithoutContentViaInfrastructureExtension" : 0,
      "roots" : [ ]
    } ]
  }
}